[
  {
    "first_name": "duck",
    "last_name": "bae",
    "id": 4902350858001,
    "index": 14,
    "display": "duck",
    "video_ally": "X",
    "video_colorblindness": "X",
    "video_diversity": "X",
    "video_person_of_color": "X",
    "video_politically_correct": "X",
    "video_racism": "X",
    "video_racist": "X",
    "video_safe_space": "X",
    "video_white_fragility": "X",
    "video_white_privilege": "X"
  },
  {
    "first_name": "autumn",
    "last_name": "bennett",
    "id": 4902336336001,
    "index": 17,
    "display": "autumn",
    "video_ally": "X",
    "video_all_lives_matter": "X",
    "video_colorblindness": "X",
    "video_diversity": "X",
    "video_microaggression": "X",
    "video_person_of_color": "X",
    "video_politically_correct": "X",
    "video_racism": "X",
    "video_racist": "X",
    "video_safe_space": "X",
    "video_white_fragility": "X",
    "video_white_privilege": "X"
  },
  {
    "first_name": "keli",
    "last_name": "carender",
    "id": 4902350869001,
    "index": 11,
    "display": "keli",
    "video_ally": "X",
    "video_all_lives_matter": "X",
    "video_colorblindness": "X",
    "video_diversity": "X",
    "video_microaggression": "X",
    "video_politically_correct": "X",
    "video_racism": "X",
    "video_racist": "X",
    "video_safe_space": "X",
    "video_white_privilege": "X"
  },
  {
    "first_name": "louis",
    "last_name": "chude-sokei",
    "id": 4902350863001,
    "index": 8,
    "display": "louis",
    "video_ally": "X",
    "video_all_lives_matter": "X",
    "video_colorblindness": "X",
    "video_diversity": "X",
    "video_microaggression": "X",
    "video_person_of_color": "X",
    "video_politically_correct": "X",
    "video_racism": "X",
    "video_racist": "X",
    "video_safe_space": "X",
    "video_white_fragility": "X",
    "video_white_privilege": "X"
  },
  {
    "first_name": "jerrell",
    "last_name": "davis",
    "id": 4902337235001,
    "index": 12,
    "display": "jerrell",
    "video_ally": "X",
    "video_all_lives_matter": "X",
    "video_colorblindness": "X",
    "video_microaggression": "X",
    "video_person_of_color": "X",
    "video_politically_correct": "X",
    "video_racism": "X",
    "video_racist": "X",
    "video_safe_space": "X",
    "video_white_fragility": "X",
    "video_white_privilege": "X"
  },
  {
    "first_name": "rachael",
    "last_name": "decruz",
    "id": 4902336344001,
    "index": 3,
    "display": "rachael",
    "video_ally": "X",
    "video_all_lives_matter": "X",
    "video_colorblindness": "X",
    "video_diversity": "X",
    "video_microaggression": "X",
    "video_person_of_color": "X",
    "video_politically_correct": "X",
    "video_racism": "X",
    "video_racist": "X",
    "video_safe_space": "X",
    "video_white_fragility": "X",
    "video_white_privilege": "X"
  },
  {
    "first_name": "michael",
    "last_name": "dixon",
    "id": 4902336343001,
    "index": 4,
    "display": "michael",
    "video_all_lives_matter": "X",
    "video_colorblindness": "X",
    "video_diversity": "X",
    "video_person_of_color": "X",
    "video_racist": "X",
    "video_safe_space": "X",
    "video_white_fragility": "X",
    "video_white_privilege": "X"
  },
  {
    "first_name": "leija",
    "last_name": "farr",
    "id": 4902350862001,
    "index": 10,
    "display": "leija",
    "video_ally": "X",
    "video_all_lives_matter": "X",
    "video_colorblindness": "X",
    "video_diversity": "X",
    "video_microaggression": "X",
    "video_safe_space": "X",
    "video_white_fragility": "X",
    "video_white_privilege": "X"
  },
  {
    "first_name": "lorena",
    "last_name": "gonzález",
    "id": 4902337237001,
    "index": 9,
    "display": "m. lorena",
    "video_ally": "X",
    "video_diversity": "X",
    "video_microaggression": "X",
    "video_person_of_color": "X",
    "video_racism": "X",
    "video_racist": "X",
    "video_white_privilege": "X"
  },
  {
    "first_name": "darrell",
    "last_name": "hillaire",
    "id": 4902350233001,
    "index": 15,
    "display": "darrell",
    "video_ally": "X",
    "video_all_lives_matter": "X",
    "video_colorblindness": "X",
    "video_person_of_color": "X",
    "video_politically_correct": "X",
    "video_racism": "X",
    "video_racist": "X",
    "video_white_fragility": "X",
    "video_white_privilege": "X"
  },
  {
    "first_name": "varisha",
    "last_name": "khan",
    "id": 4902336345001,
    "index": 0,
    "display": "varisha",
    "video_ally": "X",
    "video_colorblindness": "X",
    "video_diversity": "X",
    "video_microaggression": "X",
    "video_person_of_color": "X",
    "video_racist": "X",
    "video_safe_space": "X",
    "video_white_fragility": "X",
    "video_white_privilege": "X"
  },
  {
    "first_name": "lucas",
    "last_name": "nydam",
    "id": 4902350864001,
    "index": 7,
    "display": "lucas",
    "video_ally": "X",
    "video_all_lives_matter": "X",
    "video_colorblindness": "X",
    "video_diversity": "X",
    "video_politically_correct": "X",
    "video_racism": "X",
    "video_safe_space": "X",
    "video_white_fragility": "X",
    "video_white_privilege": "X"
  },
  {
    "first_name": "mark",
    "last_name": "olsen",
    "id": 4902350234001,
    "index": 5,
    "display": "mark",
    "video_ally": "X",
    "video_all_lives_matter": "X",
    "video_colorblindness": "X",
    "video_diversity": "X",
    "video_microaggression": "X",
    "video_politically_correct": "X",
    "video_racism": "X",
    "video_racist": "X",
    "video_white_privilege": "X"
  },
  {
    "first_name": "marci",
    "last_name": "owens",
    "id": 4902350866001,
    "index": 6,
    "display": "marci",
    "video_ally": "X",
    "video_all_lives_matter": "X",
    "video_diversity": "X",
    "video_microaggression": "X",
    "video_politically_correct": "X",
    "video_safe_space": "X",
    "video_white_fragility": "X"
  },
  {
    "first_name": "greg",
    "last_name": "rickel",
    "id": 4902350860001,
    "index": 13,
    "display": "greg",
    "video_ally": "X",
    "video_all_lives_matter": "X",
    "video_colorblindness": "X",
    "video_diversity": "X",
    "video_person_of_color": "X",
    "video_politically_correct": "X",
    "video_racism": "X",
    "video_racist": "X",
    "video_white_fragility": "X",
    "video_white_privilege": "X"
  },
  {
    "first_name": "sean",
    "last_name": "riley",
    "id": 4902350867001,
    "index": 2,
    "display": "sean",
    "video_ally": "X",
    "video_diversity": "X",
    "video_microaggression": "X",
    "video_politically_correct": "X",
    "video_racism": "X",
    "video_safe_space": "X",
    "video_white_fragility": "X",
    "video_white_privilege": "X"
  },
  {
    "first_name": "cynthia",
    "last_name": "tee",
    "id": 4902336337001,
    "index": 16,
    "display": "cynthia",
    "video_ally": "X",
    "video_all_lives_matter": "X",
    "video_colorblindness": "X",
    "video_diversity": "X",
    "video_microaggression": "X",
    "video_person_of_color": "X",
    "video_politically_correct": "X",
    "video_racism": "X",
    "video_racist": "X",
    "video_safe_space": "X",
    "video_white_fragility": "X",
    "video_white_privilege": "X"
  },
  {
    "first_name": "tariqa",
    "last_name": "waters",
    "id": 4902350856001,
    "index": 1,
    "display": "tariqa",
    "video_ally": "X",
    "video_all_lives_matter": "X",
    "video_colorblindness": "X",
    "video_microaggression": "X",
    "video_person_of_color": "X",
    "video_politically_correct": "X",
    "video_racist": "X",
    "video_safe_space": "X",
    "video_white_privilege": "X"
  }
]